azure/mgmt/subscription/__init__.py
azure/mgmt/subscription/_configuration.py
azure/mgmt/subscription/_patch.py
azure/mgmt/subscription/_serialization.py
azure/mgmt/subscription/_subscription_client.py
azure/mgmt/subscription/_vendor.py
azure/mgmt/subscription/_version.py
azure/mgmt/subscription/py.typed
azure/mgmt/subscription/aio/__init__.py
azure/mgmt/subscription/aio/_configuration.py
azure/mgmt/subscription/aio/_patch.py
azure/mgmt/subscription/aio/_subscription_client.py
azure/mgmt/subscription/aio/operations/__init__.py
azure/mgmt/subscription/aio/operations/_alias_operations.py
azure/mgmt/subscription/aio/operations/_billing_account_operations.py
azure/mgmt/subscription/aio/operations/_operations.py
azure/mgmt/subscription/aio/operations/_patch.py
azure/mgmt/subscription/aio/operations/_subscription_operations.py
azure/mgmt/subscription/aio/operations/_subscription_policy_operations.py
azure/mgmt/subscription/aio/operations/_subscriptions_operations.py
azure/mgmt/subscription/aio/operations/_tenants_operations.py
azure/mgmt/subscription/models/__init__.py
azure/mgmt/subscription/models/_models_py3.py
azure/mgmt/subscription/models/_patch.py
azure/mgmt/subscription/models/_subscription_client_enums.py
azure/mgmt/subscription/operations/__init__.py
azure/mgmt/subscription/operations/_alias_operations.py
azure/mgmt/subscription/operations/_billing_account_operations.py
azure/mgmt/subscription/operations/_operations.py
azure/mgmt/subscription/operations/_patch.py
azure/mgmt/subscription/operations/_subscription_operations.py
azure/mgmt/subscription/operations/_subscription_policy_operations.py
azure/mgmt/subscription/operations/_subscriptions_operations.py
azure/mgmt/subscription/operations/_tenants_operations.py
azure_mgmt_subscription-3.1.0.dist-info/LICENSE
azure_mgmt_subscription-3.1.0.dist-info/METADATA
azure_mgmt_subscription-3.1.0.dist-info/WHEEL
azure_mgmt_subscription-3.1.0.dist-info/top_level.txt
azure_mgmt_subscription-3.1.0.dist-info/RECORD
